aiter/__init__.py
aiter/config/__init__.py
aiter/config/config.py
aiter/config/models.yaml
aiter/config/versions.yaml
aiter/llm_api/googleai_api.py
aiter/llm_api/llm_api_call.py
aiter/llm_api/mistral_api.py
aiter/metric/reformulation.py
aiter/metric/scorer.py
aiter/metric/ter_computation.py
aiter/prompts/1/fr/correction_prompt.txt
aiter/prompts/2/fr/correction_prompt.txt
aiter/prompts/2/fr/off_topic_prompt.txt
aiter/prompts/3/en/completion_prompt.txt
aiter/prompts/3/en/correction_prompt.txt
aiter/prompts/3/en/off_topic_prompt.txt
aiter/prompts/3/fr/completion_prompt.txt
aiter/prompts/3/fr/correction_prompt.txt
aiter/prompts/3/fr/off_topic_prompt.txt
aiter/utils/__init__.py
aiter/utils/utils.py
aiter_metric-0.1.6.dist-info/licenses/LICENSE
aiter_metric-0.1.6.dist-info/METADATA
aiter_metric-0.1.6.dist-info/WHEEL
aiter_metric-0.1.6.dist-info/top_level.txt
aiter_metric-0.1.6.dist-info/RECORD
