Metadata-Version: 2.4
Name: aiter-metric
Version: 0.1.6
Summary: Métrique AITER
Author: Antoine Dieu
License: MIT
Requires-Python: >=3.9
License-File: LICENSE
Requires-Dist: pyyaml>=6
Requires-Dist: mistralai
Requires-Dist: google
Requires-Dist: google-genai
Requires-Dist: tqdm
Requires-Dist: pandas
Requires-Dist: sacrebleu
Dynamic: license-file
